moeralib/__init__.py
moeralib/pruning_validator.py
moeralib/py.typed
moeralib/structure.py
moeralib/universal_location.py
moeralib/crypto/__init__.py
moeralib/crypto/crypto.py
moeralib/crypto/fingerprint.py
moeralib/naming/__init__.py
moeralib/naming/fingerprints.py
moeralib/naming/naming.py
moeralib/naming/schemas.py
moeralib/naming/types.py
moeralib/node/__init__.py
moeralib/node/caller.py
moeralib/node/cartes.py
moeralib/node/fingerprints.py
moeralib/node/node.py
moeralib/node/schemas.py
moeralib/node/types.py
moeralib-0.17.14.dist-info/licenses/LICENSE
moeralib-0.17.14.dist-info/METADATA
moeralib-0.17.14.dist-info/WHEEL
moeralib-0.17.14.dist-info/top_level.txt
moeralib-0.17.14.dist-info/RECORD
