Metadata-Version: 2.4
Name: moeralib
Version: 0.17.14
Summary: Library to interact with Moera decentralized social network
Author-email: Shmuel Leib Melamud <balu@moera.org>
License-Expression: Apache-2.0
Project-URL: Homepage, https://github.com/MoeraOrg/python-moeralib
Project-URL: Bug Tracker, https://github.com/MoeraOrg/moera-issues/issues
Project-URL: Overview, https://moera.org
Keywords: Moera,library,naming,node,API
Classifier: Programming Language :: Python :: 3
Classifier: Operating System :: OS Independent
Classifier: Intended Audience :: Developers
Classifier: Topic :: Software Development :: Libraries :: Python Modules
Requires-Python: >=3.10
License-File: LICENSE
Requires-Dist: requests>=2.31.0
Requires-Dist: camel-converter
Requires-Dist: jsonschema>=4.19.0
Requires-Dist: cryptography~=42.0.4
Requires-Dist: mnemonic
Requires-Dist: ecpy
Dynamic: license-file
